vsb_text/__init__.py
vsb_text/vsbd.py
vsb_text-0.1.0.dist-info/METADATA
vsb_text-0.1.0.dist-info/WHEEL
vsb_text-0.1.0.dist-info/RECORD
